odoo/addons/l10n_es_account_asset/README.rst
odoo/addons/l10n_es_account_asset/__init__.py
odoo/addons/l10n_es_account_asset/__manifest__.py
odoo/addons/l10n_es_account_asset/i18n/ca.po
odoo/addons/l10n_es_account_asset/i18n/cs.po
odoo/addons/l10n_es_account_asset/i18n/de.po
odoo/addons/l10n_es_account_asset/i18n/es.po
odoo/addons/l10n_es_account_asset/i18n/es_CO.po
odoo/addons/l10n_es_account_asset/i18n/fr.po
odoo/addons/l10n_es_account_asset/i18n/fr_BE.po
odoo/addons/l10n_es_account_asset/i18n/gl.po
odoo/addons/l10n_es_account_asset/i18n/hr.po
odoo/addons/l10n_es_account_asset/i18n/l10n_es_account_asset.pot
odoo/addons/l10n_es_account_asset/i18n/pl.po
odoo/addons/l10n_es_account_asset/i18n/pt.po
odoo/addons/l10n_es_account_asset/i18n/pt_BR.po
odoo/addons/l10n_es_account_asset/i18n/ru.po
odoo/addons/l10n_es_account_asset/i18n/sl.po
odoo/addons/l10n_es_account_asset/i18n/sv.po
odoo/addons/l10n_es_account_asset/i18n/vi.po
odoo/addons/l10n_es_account_asset/models/__init__.py
odoo/addons/l10n_es_account_asset/models/account_asset.py
odoo/addons/l10n_es_account_asset/models/account_asset_profile.py
odoo/addons/l10n_es_account_asset/models/account_move.py
odoo/addons/l10n_es_account_asset/readme/CONTRIBUTORS.md
odoo/addons/l10n_es_account_asset/readme/DESCRIPTION.md
odoo/addons/l10n_es_account_asset/static/description/icon.png
odoo/addons/l10n_es_account_asset/static/description/index.html
odoo/addons/l10n_es_account_asset/tests/__init__.py
odoo/addons/l10n_es_account_asset/tests/test_create_asset_from_invoice.py
odoo/addons/l10n_es_account_asset/tests/test_l10n_es_account_asset.py
odoo/addons/l10n_es_account_asset/views/account_asset_profile_views.xml
odoo/addons/l10n_es_account_asset/views/account_asset_views.xml
odoo_addon_l10n_es_account_asset-18.0.2.0.0.1.dist-info/METADATA
odoo_addon_l10n_es_account_asset-18.0.2.0.0.1.dist-info/WHEEL
odoo_addon_l10n_es_account_asset-18.0.2.0.0.1.dist-info/top_level.txt
odoo_addon_l10n_es_account_asset-18.0.2.0.0.1.dist-info/RECORD
