Metadata-Version: 2.1
Name: odoo-addon-l10n_es_account_asset
Version: 18.0.2.0.0.1
Requires-Python: >=3.10
Requires-Dist: odoo-addon-account_asset_management==18.0.*
Requires-Dist: odoo-addon-l10n_es_aeat==18.0.*
Requires-Dist: odoo==18.0.*
Summary: =?utf-8?q?Gesti=C3=B3n_de_activos_fijos_para_Espa=C3=B1a?=
Home-page: https://github.com/OCA/l10n-spain
License: AGPL-3
Author: Tecnativa, Odoo Community Association (OCA)
Author-email: support@odoo-community.org
Classifier: Programming Language :: Python
Classifier: Framework :: Odoo
Classifier: Framework :: Odoo :: 18.0
Classifier: License :: OSI Approved :: GNU Affero General Public License v3
Classifier: Development Status :: 5 - Production/Stable
